platonic/sqs/__init__.py
platonic/sqs/py.typed
platonic/sqs/queue/__init__.py
platonic/sqs/queue/acknowledge.py
platonic/sqs/queue/errors.py
platonic/sqs/queue/message.py
platonic/sqs/queue/receiver.py
platonic/sqs/queue/sender.py
platonic/sqs/queue/sqs.py
platonic/sqs/queue/types.py
platonic_sqs-1.2.8.dist-info/LICENSE
platonic_sqs-1.2.8.dist-info/WHEEL
platonic_sqs-1.2.8.dist-info/METADATA
platonic_sqs-1.2.8.dist-info/RECORD
