Metadata-Version: 2.1
Name: platonic-sqs
Version: 1.2.8
Summary: Platonic wrapper for Amazon Simple Queue Service
Home-page: https://github.com/python-platonic/platonic-sqs
License: MIT
Requires-Python: >=3.7,<3.10
Classifier: Development Status :: 3 - Alpha
Classifier: Intended Audience :: Developers
Classifier: License :: OSI Approved :: MIT License
Classifier: Operating System :: OS Independent
Classifier: Programming Language :: Python :: 3
Classifier: Programming Language :: Python :: 3.7
Classifier: Programming Language :: Python :: 3.8
Classifier: Programming Language :: Python :: 3.9
Classifier: Topic :: Software Development :: Libraries :: Python Modules
Requires-Dist: attrs (>=20.3.0,<21.0.0)
Requires-Dist: boltons (>=20.2.1,<22.0.0)
Requires-Dist: boto3 (>=1.17.15,<2.0.0)
Requires-Dist: boto3-stubs[sqs] (>=1.15.10,<2.0.0)
Requires-Dist: botocore (>=1.20.15,<2.0.0)
Requires-Dist: mypy-boto3-sqs (>=1.17.26,<2.0.0)
Requires-Dist: platonic (>=1.2.1,<2.0.0)
Project-URL: Repository, https://github.com/python-platonic/platonic-sqs
